DecryptionToolkeet/__init__.py
DecryptionToolkeet/main.py
decryptiontoolkeet-1.0.0.dist-info/licenses/LICENSE
decryptiontoolkeet-1.0.0.dist-info/METADATA
decryptiontoolkeet-1.0.0.dist-info/WHEEL
decryptiontoolkeet-1.0.0.dist-info/top_level.txt
decryptiontoolkeet-1.0.0.dist-info/RECORD
