Metadata-Version: 2.4
Name: DecryptionToolkeet
Version: 1.0.0
Summary: A comprehensive Python CLI tool for automatically decoding and decrypting strings using classic ciphers and encodings.
Author-email: Aarav Gupta <tribejustice35@gmail.com>
License: MIT License
Project-URL: Homepage, https://github.com/Aarav2709/DecryptionToolkeet
Keywords: DecryptionToolkeet,Cryptography,Decryption,Cipher,Encoding,CTF,Security
Classifier: Development Status :: 5 - Production/Stable
Classifier: License :: OSI Approved :: MIT License
Classifier: Programming Language :: Python :: 3.13
Classifier: Intended Audience :: Education
Classifier: Operating System :: OS Independent
Requires-Python: >=3.6
License-File: LICENSE
Dynamic: license-file
